opendht/__init__.py
opendht/_core.cpython-310-x86_64-linux-gnu.so
opendht/aio.py
opendht.libs/libargon2-c656c0e3.so.1
opendht.libs/libffi-acf6d142.so.8.1.0
opendht.libs/libfmt-677b7a5c.so.8.1.1
opendht.libs/libgnutls-f707d4f6.so.30.37.1
opendht.libs/libhogweed-26d0d136.so.6.10
opendht.libs/libidn2-5237fb84.so.0.3.7
opendht.libs/libnettle-3f305521.so.8.10
opendht.libs/libopendht-d6170697.so.3.7.0
opendht.libs/libp11-kit-9eec2de8.so.0.3.1
opendht.libs/libtasn1-adfcd574.so.6.6.0
opendht.libs/libunistring-7ed7589d.so.2.1.0
opendht-3.7.0.dist-info/METADATA
opendht-3.7.0.dist-info/WHEEL
opendht-3.7.0.dist-info/top_level.txt
opendht-3.7.0.dist-info/RECORD
opendht-3.7.0.dist-info/sboms/auditwheel.cdx.json
