Metadata-Version: 2.4
Name: opendht
Version: 3.7.0
Summary: OpenDHT: A lightweight Distributed Hash Table
Home-page: https://github.com/savoirfairelinux/opendht
Author: Adrien Beraud <adrien.beraud@savoirfairelinux.com>
License: MIT
Classifier: Development Status :: 5 - Production/Stable
Classifier: Intended Audience :: Developers
Classifier: Topic :: Software Development :: Libraries :: Python Modules
Classifier: Topic :: System :: Distributed Computing
Classifier: Topic :: System :: Networking
Classifier: Programming Language :: Python :: 3
Classifier: Programming Language :: Python :: 3.9
Dynamic: author
Dynamic: classifier
Dynamic: description
Dynamic: description-content-type
Dynamic: home-page
Dynamic: license
Dynamic: summary
